luna/data_ingestion_template_schema.yml
luna/transforms.py
luna/api/__init__.py
luna/api/radiologyPreprocessingLibrary/__init__.py
luna/api/radiologyPreprocessingLibrary/app.py
luna/api/radiologyPreprocessingLibrary/service.py
luna/clinical/__init__.py
luna/clinical/proxy_table/__init__.py
luna/clinical/proxy_table/generate.py
luna/get_pathology_annotations/__init__.py
luna/integration/__init__.py
luna/pipelines/lung_radiomics_recist.yaml
luna/pipelines/qin_tcia_example.yaml
luna/pipelines/lung_radiomics_v1/collect_results_original_label.json
luna/pipelines/lung_radiomics_v1/collect_results_pertubation_label.json
luna/pipelines/lung_radiomics_v1/driver.py
luna/pipelines/lung_radiomics_v1/extract_radiomics_original_1.json
luna/pipelines/lung_radiomics_v1/extract_radiomics_original_2.json
luna/pipelines/lung_radiomics_v1/extract_radiomics_original_3.json
luna/pipelines/lung_radiomics_v1/extract_radiomics_original_4.json
luna/pipelines/lung_radiomics_v1/extract_radiomics_original_5.json
luna/pipelines/lung_radiomics_v1/extract_radiomics_original_6.json
luna/pipelines/lung_radiomics_v1/extract_radiomics_pertubation_1.json
luna/pipelines/lung_radiomics_v1/extract_radiomics_pertubation_2.json
luna/pipelines/lung_radiomics_v1/extract_radiomics_pertubation_3.json
luna/pipelines/lung_radiomics_v1/extract_radiomics_pertubation_4.json
luna/pipelines/lung_radiomics_v1/extract_radiomics_pertubation_5.json
luna/pipelines/lung_radiomics_v1/extract_radiomics_pertubation_6.json
luna/pipelines/lung_radiomics_v1/generate_scan.json
luna/pipelines/lung_radiomics_v1/load_dicom.json
luna/pipelines/lung_radiomics_v1/randomize_contours.json
luna/pipelines/run_eng_inference/driver.py
luna/pipelines/run_eng_inference/infer_tile_labels_resnet18.json
luna/pipelines/run_eng_inference/visualize_model_inference.json
luna/pipelines/run_ov_inference/driver.py
luna/pipelines/run_ov_inference/infer_tile_labels_resnet18.json
luna/pipelines/run_ov_inference/visualize_model_inference.json
pyluna_core-0.3.3.dist-info/METADATA
pyluna_core-0.3.3.dist-info/WHEEL
pyluna_core-0.3.3.dist-info/top_level.txt
pyluna_core-0.3.3.dist-info/zip-safe
pyluna_core-0.3.3.dist-info/RECORD
